{
	"archive" : {},
	"artifacts" : 
	[
		{
			"path" : "module/controller/libraibot_default_controller.a"
		}
	],
	"backtrace" : 2,
	"backtraceGraph" : 
	{
		"commands" : 
		[
			"add_library",
			"create_controller"
		],
		"files" : 
		[
			"module/controller/CMakeLists.txt"
		],
		"nodes" : 
		[
			{
				"file" : 0
			},
			{
				"command" : 1,
				"file" : 0,
				"line" : 35,
				"parent" : 0
			},
			{
				"command" : 0,
				"file" : 0,
				"line" : 25,
				"parent" : 1
			}
		]
	},
	"id" : "raibot_default_controller::@889be60e461c32ea4f6d",
	"name" : "raibot_default_controller",
	"nameOnDisk" : "libraibot_default_controller.a",
	"paths" : 
	{
		"build" : "module/controller",
		"source" : "module/controller"
	},
	"sourceGroups" : 
	[
		{
			"name" : "Header Files",
			"sourceIndexes" : 
			[
				0
			]
		}
	],
	"sources" : 
	[
		{
			"backtrace" : 2,
			"path" : "module/controller/raibot_default_controller/raibot_default_controller.hpp",
			"sourceGroupIndex" : 0
		}
	],
	"type" : "STATIC_LIBRARY"
}
